{
  "0x316ec86a5549f8df0cf046ecc586ea5a8b18bf9b": {
    "address": "0x316ec86a5549f8df0cf046ecc586ea5a8b18bf9b",
    "available_rank_variables": [
      "transactions",
      "gas_used",
      "native_volume",
      "overall_rank"
    ],
    "first_seen_block": 14966900,
    "last_seen_block": 14966900,
    "metrics": {
      "collection_diversity": null,
      "gas_used": 0,
      "low_sybil_risk": null,
      "native_funds": null,
      "native_volume": "0.000111867477408865",
      "nft_holdings": null,
      "reputation_score": null,
      "transactions": 0
    },
    "pending_rank_variables": [
      "native_funds",
      "nft_holdings",
      "collection_diversity",
      "reputation_score",
      "low_sybil_risk"
    ],
    "percentiles": {
      "collection_diversity": null,
      "gas_used": "79.109589",
      "low_sybil_risk": null,
      "native_funds": null,
      "native_volume": "79.366438",
      "nft_holdings": null,
      "overall_rank": "89.640411",
      "reputation_score": null,
      "transactions": "79.109589"
    },
    "rank_tier": "INDEXED",
    "ranks": {
      "collection_diversity": null,
      "gas_used": 924,
      "low_sybil_risk": null,
      "native_funds": null,
      "native_volume": 927,
      "nft_holdings": null,
      "overall_rank": 1047,
      "reputation_score": null,
      "transactions": 924
    },
    "strongest_metric": "transactions",
    "total_ranked_wallets": 1168,
    "updated_at": "2026-06-06T21:19:46+00:00"
  },
  "0x318ec26fd23af1b5e913c606c7becd56b9b0d651": {
    "address": "0x318ec26fd23af1b5e913c606c7becd56b9b0d651",
    "available_rank_variables": [
      "transactions",
      "gas_used",
      "native_volume",
      "overall_rank"
    ],
    "first_seen_block": 14966899,
    "last_seen_block": 14966899,
    "metrics": {
      "collection_diversity": null,
      "gas_used": 0,
      "low_sybil_risk": null,
      "native_funds": null,
      "native_volume": "0.086",
      "nft_holdings": null,
      "reputation_score": null,
      "transactions": 0
    },
    "pending_rank_variables": [
      "native_funds",
      "nft_holdings",
      "collection_diversity",
      "reputation_score",
      "low_sybil_risk"
    ],
    "percentiles": {
      "collection_diversity": null,
      "gas_used": "79.195205",
      "low_sybil_risk": null,
      "native_funds": null,
      "native_volume": "27.226027",
      "nft_holdings": null,
      "overall_rank": "68.065068",
      "reputation_score": null,
      "transactions": "79.195205"
    },
    "rank_tier": "TOP_50_PERCENT",
    "ranks": {
      "collection_diversity": null,
      "gas_used": 925,
      "low_sybil_risk": null,
      "native_funds": null,
      "native_volume": 318,
      "nft_holdings": null,
      "overall_rank": 795,
      "reputation_score": null,
      "transactions": 925
    },
    "strongest_metric": "native_volume",
    "total_ranked_wallets": 1168,
    "updated_at": "2026-06-06T21:46:55+00:00"
  },
  "0x31a6775a88aa9f5481698b0829a0038909df222f": {
    "address": "0x31a6775a88aa9f5481698b0829a0038909df222f",
    "available_rank_variables": [
      "transactions",
      "gas_used",
      "native_volume",
      "overall_rank"
    ],
    "first_seen_block": 14966910,
    "last_seen_block": 14966910,
    "metrics": {
      "collection_diversity": null,
      "gas_used": 0,
      "low_sybil_risk": null,
      "native_funds": null,
      "native_volume": "0.001266625074009623",
      "nft_holdings": null,
      "reputation_score": null,
      "transactions": 0
    },
    "pending_rank_variables": [
      "native_funds",
      "nft_holdings",
      "collection_diversity",
      "reputation_score",
      "low_sybil_risk"
    ],
    "percentiles": {
      "collection_diversity": null,
      "gas_used": "79.280822",
      "low_sybil_risk": null,
      "native_funds": null,
      "native_volume": "65.325342",
      "nft_holdings": null,
      "overall_rank": "85.787671",
      "reputation_score": null,
      "transactions": "79.280822"
    },
    "rank_tier": "INDEXED",
    "ranks": {
      "collection_diversity": null,
      "gas_used": 926,
      "low_sybil_risk": null,
      "native_funds": null,
      "native_volume": 763,
      "nft_holdings": null,
      "overall_rank": 1002,
      "reputation_score": null,
      "transactions": 926
    },
    "strongest_metric": "native_volume",
    "total_ranked_wallets": 1168,
    "updated_at": "2026-06-06T20:03:42+00:00"
  },
  "0x31fa2e205945dd4d1c5427f64f33f99bb44dd61f": {
    "address": "0x31fa2e205945dd4d1c5427f64f33f99bb44dd61f",
    "available_rank_variables": [
      "transactions",
      "gas_used",
      "native_volume",
      "overall_rank"
    ],
    "first_seen_block": 14966899,
    "last_seen_block": 14966899,
    "metrics": {
      "collection_diversity": null,
      "gas_used": 0,
      "low_sybil_risk": null,
      "native_funds": null,
      "native_volume": "0.01",
      "nft_holdings": null,
      "reputation_score": null,
      "transactions": 0
    },
    "pending_rank_variables": [
      "native_funds",
      "nft_holdings",
      "collection_diversity",
      "reputation_score",
      "low_sybil_risk"
    ],
    "percentiles": {
      "collection_diversity": null,
      "gas_used": "79.366438",
      "low_sybil_risk": null,
      "native_funds": null,
      "native_volume": "44.178082",
      "nft_holdings": null,
      "overall_rank": "77.996575",
      "reputation_score": null,
      "transactions": "79.366438"
    },
    "rank_tier": "TOP_50_PERCENT",
    "ranks": {
      "collection_diversity": null,
      "gas_used": 927,
      "low_sybil_risk": null,
      "native_funds": null,
      "native_volume": 516,
      "nft_holdings": null,
      "overall_rank": 911,
      "reputation_score": null,
      "transactions": 927
    },
    "strongest_metric": "native_volume",
    "total_ranked_wallets": 1168,
    "updated_at": "2026-06-06T21:19:46+00:00"
  }
}
